x5qautils/__init__.py
x5qautils/exceptions.py
x5qautils/api/__init__.py
x5qautils/api/async_microservices.py
x5qautils/api/content_type.py
x5qautils/api/keycloak_auth.py
x5qautils/api/log_request.py
x5qautils/api/microservices.py
x5qautils/api/model.py
x5qautils/db_tools/__init__.py
x5qautils/db_tools/click_db.py
x5qautils/db_tools/db.py
x5qautils/helpers/__init__.py
x5qautils/helpers/async_tools.py
x5qautils/helpers/exel.py
x5qautils/helpers/tools.py
x5qautils/kafka/__init__.py
x5qautils/kafka/kafka.py
x5qautils/ui/__init__.py
x5qautils/ui/auth.py
x5qautils/ui/base_page_interface.py
x5qautils/ui/common.py
x5qautils/ui/session.py
x5qautils-3.1.0.dist-info/METADATA
x5qautils-3.1.0.dist-info/WHEEL
x5qautils-3.1.0.dist-info/top_level.txt
x5qautils-3.1.0.dist-info/RECORD
